pytta/__init__.py
pytta/_h5utils.py
pytta/_plot.py
pytta/_properties.py
pytta/functions.py
pytta/generate.py
pytta/iso3741.py
pytta/rooms.py
pytta/apps/__init__.py
pytta/apps/roomir.py
pytta/classes/__init__.py
pytta/classes/_base.py
pytta/classes/_instanceinfo.py
pytta/classes/analysis.py
pytta/classes/ei1050.py
pytta/classes/filter.py
pytta/classes/lju3ei1050.py
pytta/classes/measurement.py
pytta/classes/signal.py
pytta/classes/streaming.py
pytta/utils/__init__.py
pytta/utils/colore.py
pytta/utils/freq.py
pytta/utils/maths.py
PyTTa-0.1.1.dist-info/LICENSE
PyTTa-0.1.1.dist-info/METADATA
PyTTa-0.1.1.dist-info/WHEEL
PyTTa-0.1.1.dist-info/top_level.txt
PyTTa-0.1.1.dist-info/RECORD
