Metadata-Version: 2.1
Name: PyTTa
Version: 0.1.1
Summary: Signal processing tools for acoustics and vibrations in python, development package.
Home-page: http://github.com/PyTTAmaster/PyTTa
Author: João Vitor Paes, Matheus Lazarin, Marcos Reis
Author-email: pytta@eac.ufsm.br
License: MIT
Platform: UNKNOWN
Classifier: Programming Language :: Python :: 3.6
Classifier: Programming Language :: Python :: 3.7
Classifier: Programming Language :: Python :: 3.8
Classifier: License :: OSI Approved :: MIT License
Classifier: Operating System :: OS Independent
Requires-Python: >=3.6, <3.9
License-File: LICENSE
Requires-Dist: numpy
Requires-Dist: scipy
Requires-Dist: matplotlib
Requires-Dist: sounddevice
Requires-Dist: soundfile
Requires-Dist: h5py
Requires-Dist: numba
